novel_updates_scraper/Book.py
novel_updates_scraper/Search.py
novel_updates_scraper/__init__.py
novel_updates_scraper/cf_bypass.py
novel_updates_scraper/constants.py
novel_updates_scraper/genre_constants.py
novel_updates_scraper/get_genres.py
novel_updates_scraper/get_tags.py
novel_updates_scraper/query_constants.py
novel_updates_scraper/scraper.py
novel_updates_scraper/tag_constants.py
novel_updates_scraper/utils.py
novel_updates_scraper-0.1.8.dist-info/licenses/LICENSE
novel_updates_scraper-0.1.8.dist-info/METADATA
novel_updates_scraper-0.1.8.dist-info/WHEEL
novel_updates_scraper-0.1.8.dist-info/top_level.txt
novel_updates_scraper-0.1.8.dist-info/RECORD
